<Orders id="123456789">
  <Order CustomerCode="ALFA"
    Number="123">
    <DeliveryPlace>
      <Address City="KLADNO"
        House="5"
        Street="KLADENSKÁ"
        ZIP="54321"/>
    </DeliveryPlace>
    <Item Price="4680.0"
      ProductCode="0002"
      Quantity="2"/>
    <Item Price="3455.0"
      ProductCode="0003"
      Quantity="1"/>
  </Order>
  <Order CustomerCode="BETA"
    Number="124">
    <DeliveryPlace>
      <Address City="MĚLNÍK"
        House="5"
        Street="MĚLNICKÁ"
        ZIP="45321"/>
    </DeliveryPlace>
    <Item Price="602.5"
      ProductCode="0001"
      Quantity="5"/>
  </Order>
</Orders>